{
  "CLASS_NAME": "Choice",
  "text_html": "Звідки знаєш про курс",
  "is_multiple_choice": true,
  "is_always_correct": false,
  "preserve_order": false,
  "is_html_enabled": false,
  "is_options_feedback": false,
  "sample_size": 5,
  "answers": [
    {
      "is_correct": true,
      "text": "Из социальных сетей",
      "feedback": ""
    },
    {
      "is_correct": true,
      "text": "Из рассылки Stepik",
      "feedback": ""
    },
    {
      "is_correct": false,
      "text": "Из поисковых систем (Google, Yandex, Bing)",
      "feedback": ""
    },
    {
      "is_correct": false,
      "text": "Посоветовали друзья/коллеги",
      "feedback": ""
    },
    {
      "is_correct": false,
      "text": "Інше",
      "feedback": ""
    }
  ]
}